removalist/__init__.py
removalist/bootstrap.py
removalist/main.py
removalist/controllers/__init__.py
removalist/controllers/base.py
removalist/controllers/dependencies.py
removalist/controllers/template.py
removalist/core/__init__.py
removalist/core/exc.py
removalist/core/version.py
removalist/ext/__init__.py
removalist/plugins/__init__.py
removalist/templates/__init__.py
removalist/templates/command1.jinja2
removalist-1.0.0.dist-info/LICENSE.md
removalist-1.0.0.dist-info/METADATA
removalist-1.0.0.dist-info/WHEEL
removalist-1.0.0.dist-info/entry_points.txt
removalist-1.0.0.dist-info/top_level.txt
removalist-1.0.0.dist-info/RECORD
