Metadata-Version: 2.1
Name: removalist
Version: 1.0.0
Summary: Add Dependencies and Extensions for Hashicorp Packer
Home-page: https://github.com/convenia/removalist
Author: Bruno Briante
Author-email: bruno.briante@convenia.com.br
License: MIT
Platform: UNKNOWN
